{
  "season": 2021,
  "teams": [
    {
      "rank": 1,
      "team_name": "Danielle Macdonald",
      "total": 440,
      "doubles": 208,
      "homers": 232
    },
    {
      "rank": 2,
      "team_name": "Dan Barfknecht #1",
      "total": 431,
      "doubles": 226,
      "homers": 205
    },
    {
      "rank": 3,
      "team_name": "Troy Gemmill #2",
      "total": 429,
      "doubles": 206,
      "homers": 223
    },
    {
      "rank": 4,
      "team_name": "Justin Fryklund",
      "total": 424,
      "doubles": 216,
      "homers": 208
    },
    {
      "rank": 5,
      "team_name": "Kevin Powell",
      "total": 423,
      "doubles": 201,
      "homers": 222
    },
    {
      "rank": 6,
      "team_name": "Debbie Hins #1",
      "total": 419,
      "doubles": 218,
      "homers": 201
    },
    {
      "rank": 7,
      "team_name": "Brian Chase #2",
      "total": 414,
      "doubles": 210,
      "homers": 204
    },
    {
      "rank": 8,
      "team_name": "Debbie Hins #2",
      "total": 412,
      "doubles": 213,
      "homers": 199
    },
    {
      "rank": 9,
      "team_name": "Conner Tokheim",
      "total": 411,
      "doubles": 184,
      "homers": 227
    },
    {
      "rank": 10,
      "team_name": "Jake Johnson #1",
      "total": 406,
      "doubles": 198,
      "homers": 208
    },
    {
      "rank": 11,
      "team_name": "Cory \"NoDak\" Abrahamson #1",
      "total": 404,
      "doubles": 200,
      "homers": 204
    },
    {
      "rank": 12,
      "team_name": "Brian McBride",
      "total": 395,
      "doubles": 201,
      "homers": 194
    },
    {
      "rank": 13,
      "team_name": "Jon James #1",
      "total": 393,
      "doubles": 190,
      "homers": 203
    },
    {
      "rank": 14,
      "team_name": "Shane \"Hoffa\" Hoeft #3",
      "total": 392,
      "doubles": 177,
      "homers": 215
    },
    {
      "rank": 15,
      "team_name": "Shane \"Hoffa\" Hoeft #4",
      "total": 388,
      "doubles": 179,
      "homers": 209
    },
    {
      "rank": 15,
      "team_name": "Justin Bridge #1",
      "total": 388,
      "doubles": 189,
      "homers": 199
    },
    {
      "rank": 15,
      "team_name": "Cory \"NoDak\" Abrahamson #3",
      "total": 388,
      "doubles": 181,
      "homers": 207
    },
    {
      "rank": 18,
      "team_name": "Denny Graves #1",
      "total": 385,
      "doubles": 180,
      "homers": 205
    },
    {
      "rank": 18,
      "team_name": "Clint Shepherd",
      "total": 385,
      "doubles": 196,
      "homers": 189
    },
    {
      "rank": 20,
      "team_name": "Sara Dobervich #1",
      "total": 382,
      "doubles": 180,
      "homers": 202
    },
    {
      "rank": 21,
      "team_name": "Mark & Diane Walters",
      "total": 379,
      "doubles": 198,
      "homers": 181
    },
    {
      "rank": 22,
      "team_name": "\"Dolla\" Bill Schuldt #3",
      "total": 372,
      "doubles": 189,
      "homers": 183
    },
    {
      "rank": 23,
      "team_name": "Troy Gemmill #4",
      "total": 362,
      "doubles": 181,
      "homers": 181
    },
    {
      "rank": 23,
      "team_name": "Matt Mick",
      "total": 362,
      "doubles": 179,
      "homers": 183
    },
    {
      "rank": 25,
      "team_name": "Karl Pohl",
      "total": 360,
      "doubles": 175,
      "homers": 185
    },
    {
      "rank": 26,
      "team_name": "Ryan \"Opie\" Dahl #3",
      "total": 359,
      "doubles": 174,
      "homers": 185
    },
    {
      "rank": 26,
      "team_name": "Adam Gray #1",
      "total": 359,
      "doubles": 183,
      "homers": 176
    },
    {
      "rank": 28,
      "team_name": "Mike Erickson",
      "total": 356,
      "doubles": 182,
      "homers": 174
    },
    {
      "rank": 29,
      "team_name": "Ryan \"Opie\" Dahl #1",
      "total": 353,
      "doubles": 190,
      "homers": 163
    },
    {
      "rank": 30,
      "team_name": "Shane \"Hoffa\" Hoeft #2",
      "total": 350,
      "doubles": 182,
      "homers": 168
    },
    {
      "rank": 30,
      "team_name": "Brett Walters & Eric Miras",
      "total": 350,
      "doubles": 183,
      "homers": 167
    },
    {
      "rank": 32,
      "team_name": "Tim Schaaf",
      "total": 349,
      "doubles": 152,
      "homers": 197
    },
    {
      "rank": 33,
      "team_name": "Dan Barfknecht #2",
      "total": 347,
      "doubles": 175,
      "homers": 172
    },
    {
      "rank": 34,
      "team_name": "Eric Walters & Tom Murray #1",
      "total": 345,
      "doubles": 166,
      "homers": 179
    },
    {
      "rank": 35,
      "team_name": "Nikki Walters",
      "total": 343,
      "doubles": 158,
      "homers": 185
    },
    {
      "rank": 35,
      "team_name": "John Hackett #1",
      "total": 343,
      "doubles": 167,
      "homers": 176
    },
    {
      "rank": 37,
      "team_name": "Justin Bridge #2",
      "total": 340,
      "doubles": 176,
      "homers": 164
    },
    {
      "rank": 38,
      "team_name": "Eric Walters & Tom Murray #2",
      "total": 336,
      "doubles": 179,
      "homers": 157
    },
    {
      "rank": 39,
      "team_name": "John Hackett #2",
      "total": 333,
      "doubles": 170,
      "homers": 163
    },
    {
      "rank": 40,
      "team_name": "Ryan \"Opie\" Dahl #2",
      "total": 331,
      "doubles": 177,
      "homers": 154
    },
    {
      "rank": 41,
      "team_name": "Jake Johnson #2",
      "total": 330,
      "doubles": 164,
      "homers": 166
    },
    {
      "rank": 42,
      "team_name": "Ryan \"Wally\" Walters",
      "total": 327,
      "doubles": 165,
      "homers": 162
    },
    {
      "rank": 42,
      "team_name": "Dan Pastorino",
      "total": 327,
      "doubles": 165,
      "homers": 162
    },
    {
      "rank": 44,
      "team_name": "Jake Luedtke",
      "total": 326,
      "doubles": 167,
      "homers": 159
    },
    {
      "rank": 45,
      "team_name": "Julie Mick",
      "total": 321,
      "doubles": 164,
      "homers": 157
    },
    {
      "rank": 45,
      "team_name": "Jim & Carol Murray",
      "total": 321,
      "doubles": 187,
      "homers": 134
    },
    {
      "rank": 45,
      "team_name": "Brian Phillips",
      "total": 321,
      "doubles": 161,
      "homers": 160
    },
    {
      "rank": 48,
      "team_name": "Sara Dobervich #2",
      "total": 319,
      "doubles": 149,
      "homers": 170
    },
    {
      "rank": 48,
      "team_name": "Nic Waletich",
      "total": 319,
      "doubles": 162,
      "homers": 157
    },
    {
      "rank": 50,
      "team_name": "Duane Ebert",
      "total": 318,
      "doubles": 157,
      "homers": 161
    },
    {
      "rank": 51,
      "team_name": "\"Dolla\" Bill Schuldt #1",
      "total": 315,
      "doubles": 159,
      "homers": 156
    },
    {
      "rank": 52,
      "team_name": "Dennis Barton",
      "total": 310,
      "doubles": 158,
      "homers": 152
    },
    {
      "rank": 53,
      "team_name": "Denny Graves #2",
      "total": 303,
      "doubles": 167,
      "homers": 136
    },
    {
      "rank": 54,
      "team_name": "Jim Macdonald",
      "total": 299,
      "doubles": 147,
      "homers": 152
    },
    {
      "rank": 55,
      "team_name": "Brian Chase #1",
      "total": 298,
      "doubles": 146,
      "homers": 152
    },
    {
      "rank": 56,
      "team_name": "Cory \"NoDak\" Abrahamson #2",
      "total": 297,
      "doubles": 147,
      "homers": 150
    },
    {
      "rank": 57,
      "team_name": "Mark Smith",
      "total": 296,
      "doubles": 150,
      "homers": 146
    },
    {
      "rank": 57,
      "team_name": "Adam Gray #2",
      "total": 296,
      "doubles": 152,
      "homers": 144
    },
    {
      "rank": 59,
      "team_name": "Troy Gemmill #3",
      "total": 294,
      "doubles": 148,
      "homers": 146
    },
    {
      "rank": 59,
      "team_name": "Ryan Mortensen",
      "total": 294,
      "doubles": 163,
      "homers": 131
    },
    {
      "rank": 61,
      "team_name": "Troy Gemmill #1",
      "total": 288,
      "doubles": 154,
      "homers": 134
    },
    {
      "rank": 62,
      "team_name": "\"Dolla\" Bill Schuldt #2",
      "total": 287,
      "doubles": 141,
      "homers": 146
    },
    {
      "rank": 63,
      "team_name": "Jon James #2",
      "total": 284,
      "doubles": 155,
      "homers": 129
    },
    {
      "rank": 64,
      "team_name": "Anders Schmidt",
      "total": 283,
      "doubles": 123,
      "homers": 160
    },
    {
      "rank": 65,
      "team_name": "Braden Mick",
      "total": 279,
      "doubles": 156,
      "homers": 123
    },
    {
      "rank": 66,
      "team_name": "Shane \"Hoffa\" Hoeft #1",
      "total": 275,
      "doubles": 143,
      "homers": 132
    },
    {
      "rank": 67,
      "team_name": "Adan Pachon",
      "total": 266,
      "doubles": 132,
      "homers": 134
    },
    {
      "rank": 68,
      "team_name": "Jenny Schmidt",
      "total": 258,
      "doubles": 139,
      "homers": 119
    }
  ]
}