{
  "updated": "2026-04-06",
  "teams": [
    {
      "rank": 1,
      "owner": "Dustin Dupont",
      "team_name": "BangBang2",
      "doubles": 15,
      "homers": 14,
      "total": 29,
      "prev_rank": 1,
      "prev_doubles": 0,
      "prev_homers": 1,
      "prev_total": 28,
      "rank_change": 0,
      "total_change": 1
    },
    {
      "rank": 2,
      "owner": "Jim Macdonald",
      "team_name": "Hats For Bats",
      "doubles": 13,
      "homers": 15,
      "total": 28,
      "prev_rank": 2,
      "prev_doubles": 1,
      "prev_homers": 2,
      "prev_total": 25,
      "rank_change": 0,
      "total_change": 3
    },
    {
      "rank": 3,
      "owner": "Cory Abrahamson",
      "team_name": "Nodak 2",
      "doubles": 16,
      "homers": 10,
      "total": 26,
      "prev_rank": 3,
      "prev_doubles": 1,
      "prev_homers": 1,
      "prev_total": 24,
      "rank_change": 0,
      "total_change": 2
    },
    {
      "rank": 3,
      "owner": "Tim Brumm",
      "team_name": "Honey Badger #2",
      "doubles": 14,
      "homers": 12,
      "total": 26,
      "prev_rank": 8,
      "prev_doubles": 2,
      "prev_homers": 3,
      "prev_total": 21,
      "rank_change": 5,
      "total_change": 5
    },
    {
      "rank": 3,
      "owner": "Ryan Priestley",
      "team_name": "Ryan Priestley",
      "doubles": 13,
      "homers": 13,
      "total": 26,
      "prev_rank": 4,
      "prev_doubles": 1,
      "prev_homers": 2,
      "prev_total": 23,
      "rank_change": 1,
      "total_change": 3
    },
    {
      "rank": 6,
      "owner": "Jake Luedtke",
      "team_name": "JD's AL Sluggers",
      "doubles": 16,
      "homers": 9,
      "total": 25,
      "prev_rank": 4,
      "prev_doubles": 1,
      "prev_homers": 1,
      "prev_total": 23,
      "rank_change": -2,
      "total_change": 2
    },
    {
      "rank": 6,
      "owner": "Becky Friedrich",
      "team_name": "Sons Of Pitches",
      "doubles": 13,
      "homers": 12,
      "total": 25,
      "prev_rank": 16,
      "prev_doubles": 2,
      "prev_homers": 5,
      "prev_total": 18,
      "rank_change": 10,
      "total_change": 7
    },
    {
      "rank": 8,
      "owner": "Dan Barfknecht",
      "team_name": "Dan Barfknecht #2",
      "doubles": 15,
      "homers": 9,
      "total": 24,
      "prev_rank": 8,
      "prev_doubles": 2,
      "prev_homers": 1,
      "prev_total": 21,
      "rank_change": 0,
      "total_change": 3
    },
    {
      "rank": 8,
      "owner": "Jim Macdonald",
      "team_name": "Crisco, Bardol, Vagisil",
      "doubles": 12,
      "homers": 12,
      "total": 24,
      "prev_rank": 6,
      "prev_doubles": 1,
      "prev_homers": 1,
      "prev_total": 22,
      "rank_change": -2,
      "total_change": 2
    },
    {
      "rank": 10,
      "owner": "Teresa Demma",
      "team_name": "Demma-lition",
      "doubles": 12,
      "homers": 11,
      "total": 23,
      "prev_rank": 11,
      "prev_doubles": 1,
      "prev_homers": 3,
      "prev_total": 19,
      "rank_change": 1,
      "total_change": 4
    },
    {
      "rank": 10,
      "owner": "Jon James",
      "team_name": "Jon James #2",
      "doubles": 12,
      "homers": 11,
      "total": 23,
      "prev_rank": 8,
      "prev_doubles": 2,
      "prev_homers": 0,
      "prev_total": 21,
      "rank_change": -2,
      "total_change": 2
    },
    {
      "rank": 10,
      "owner": "Joe Priestley",
      "team_name": "Joe Priestley #1",
      "doubles": 12,
      "homers": 11,
      "total": 23,
      "prev_rank": 11,
      "prev_doubles": 1,
      "prev_homers": 3,
      "prev_total": 19,
      "rank_change": 1,
      "total_change": 4
    },
    {
      "rank": 10,
      "owner": "Jim Macdonald",
      "team_name": "Jobu's Rum",
      "doubles": 11,
      "homers": 12,
      "total": 23,
      "prev_rank": 6,
      "prev_doubles": 0,
      "prev_homers": 1,
      "prev_total": 22,
      "rank_change": -4,
      "total_change": 1
    },
    {
      "rank": 10,
      "owner": "Kim Hackett",
      "team_name": "Shotime Sluggers",
      "doubles": 11,
      "homers": 12,
      "total": 23,
      "prev_rank": 19,
      "prev_doubles": 2,
      "prev_homers": 4,
      "prev_total": 17,
      "rank_change": 9,
      "total_change": 6
    },
    {
      "rank": 10,
      "owner": "Wendy Sheridan",
      "team_name": "Wendy\u2019s Sluggers",
      "doubles": 9,
      "homers": 14,
      "total": 23,
      "prev_rank": 16,
      "prev_doubles": 1,
      "prev_homers": 4,
      "prev_total": 18,
      "rank_change": 6,
      "total_change": 5
    },
    {
      "rank": 16,
      "owner": "Adan Pachon",
      "team_name": "APM 2",
      "doubles": 14,
      "homers": 8,
      "total": 22,
      "prev_rank": 11,
      "prev_doubles": 2,
      "prev_homers": 1,
      "prev_total": 19,
      "rank_change": -5,
      "total_change": 3
    },
    {
      "rank": 16,
      "owner": "Conner Tokheim",
      "team_name": "Conner Tokheim #1",
      "doubles": 9,
      "homers": 13,
      "total": 22,
      "prev_rank": 11,
      "prev_doubles": 1,
      "prev_homers": 2,
      "prev_total": 19,
      "rank_change": -5,
      "total_change": 3
    },
    {
      "rank": 18,
      "owner": "Ryan Dahl \ud83c\udfc6\ud83c\udfc6\ud83c\udfc6 ('19,'23,'24)",
      "team_name": "Ryan \u201cOpie\u201d Dahl #2",
      "doubles": 12,
      "homers": 9,
      "total": 21,
      "prev_rank": 19,
      "prev_doubles": 1,
      "prev_homers": 3,
      "prev_total": 17,
      "rank_change": 1,
      "total_change": 4
    },
    {
      "rank": 18,
      "owner": "Thomas Olson",
      "team_name": "Double Down",
      "doubles": 11,
      "homers": 10,
      "total": 21,
      "prev_rank": 16,
      "prev_doubles": 2,
      "prev_homers": 1,
      "prev_total": 18,
      "rank_change": -2,
      "total_change": 3
    },
    {
      "rank": 18,
      "owner": "Denny Graves",
      "team_name": "Denny Graves",
      "doubles": 11,
      "homers": 10,
      "total": 21,
      "prev_rank": 23,
      "prev_doubles": 1,
      "prev_homers": 4,
      "prev_total": 16,
      "rank_change": 5,
      "total_change": 5
    },
    {
      "rank": 18,
      "owner": "Debbie Hins",
      "team_name": "Debbie #2",
      "doubles": 11,
      "homers": 10,
      "total": 21,
      "prev_rank": 11,
      "prev_doubles": 2,
      "prev_homers": 0,
      "prev_total": 19,
      "rank_change": -7,
      "total_change": 2
    },
    {
      "rank": 22,
      "owner": "Dennis L. Graves",
      "team_name": "Florida Burn",
      "doubles": 13,
      "homers": 7,
      "total": 20,
      "prev_rank": 23,
      "prev_doubles": 2,
      "prev_homers": 2,
      "prev_total": 16,
      "rank_change": 1,
      "total_change": 4
    },
    {
      "rank": 22,
      "owner": "Joe Epple",
      "team_name": "Chasing Dahl",
      "doubles": 12,
      "homers": 8,
      "total": 20,
      "prev_rank": 23,
      "prev_doubles": 2,
      "prev_homers": 2,
      "prev_total": 16,
      "rank_change": 1,
      "total_change": 4
    },
    {
      "rank": 22,
      "owner": "Mort Mortensen",
      "team_name": "Insert Team Name Here",
      "doubles": 10,
      "homers": 10,
      "total": 20,
      "prev_rank": 23,
      "prev_doubles": 1,
      "prev_homers": 3,
      "prev_total": 16,
      "rank_change": 1,
      "total_change": 4
    },
    {
      "rank": 25,
      "owner": "Jeff Palm",
      "team_name": "Last place",
      "doubles": 14,
      "homers": 5,
      "total": 19,
      "prev_rank": 34,
      "prev_doubles": 2,
      "prev_homers": 2,
      "prev_total": 15,
      "rank_change": 9,
      "total_change": 4
    },
    {
      "rank": 25,
      "owner": "Jacob Larson",
      "team_name": "Deets",
      "doubles": 13,
      "homers": 6,
      "total": 19,
      "prev_rank": 23,
      "prev_doubles": 2,
      "prev_homers": 1,
      "prev_total": 16,
      "rank_change": -2,
      "total_change": 3
    },
    {
      "rank": 25,
      "owner": "Ian Sullivan",
      "team_name": "Ian Sullivan 1",
      "doubles": 13,
      "homers": 6,
      "total": 19,
      "prev_rank": 19,
      "prev_doubles": 1,
      "prev_homers": 1,
      "prev_total": 17,
      "rank_change": -6,
      "total_change": 2
    },
    {
      "rank": 25,
      "owner": "Brian McBride",
      "team_name": "Brian McBride  #2",
      "doubles": 11,
      "homers": 8,
      "total": 19,
      "prev_rank": 42,
      "prev_doubles": 4,
      "prev_homers": 1,
      "prev_total": 14,
      "rank_change": 17,
      "total_change": 5
    },
    {
      "rank": 25,
      "owner": "Thomas Murray",
      "team_name": "Eric Walters & Tom Murray #2",
      "doubles": 11,
      "homers": 8,
      "total": 19,
      "prev_rank": 23,
      "prev_doubles": 3,
      "prev_homers": 0,
      "prev_total": 16,
      "rank_change": -2,
      "total_change": 3
    },
    {
      "rank": 25,
      "owner": "Jim Macdonald",
      "team_name": "California Penal League",
      "doubles": 10,
      "homers": 9,
      "total": 19,
      "prev_rank": 23,
      "prev_doubles": 2,
      "prev_homers": 1,
      "prev_total": 16,
      "rank_change": -2,
      "total_change": 3
    },
    {
      "rank": 25,
      "owner": "Ryan Dahl \ud83c\udfc6\ud83c\udfc6\ud83c\udfc6 ('19,'23,'24)",
      "team_name": "Ryan \u201cOpie\u201d Dahl #1",
      "doubles": 10,
      "homers": 9,
      "total": 19,
      "prev_rank": 42,
      "prev_doubles": 1,
      "prev_homers": 4,
      "prev_total": 14,
      "rank_change": 17,
      "total_change": 5
    },
    {
      "rank": 25,
      "owner": "Cody Eichmeier",
      "team_name": "Thanks for Judge!",
      "doubles": 8,
      "homers": 11,
      "total": 19,
      "prev_rank": 23,
      "prev_doubles": 1,
      "prev_homers": 2,
      "prev_total": 16,
      "rank_change": -2,
      "total_change": 3
    },
    {
      "rank": 25,
      "owner": "Adan Pachon",
      "team_name": "APM 1",
      "doubles": 8,
      "homers": 11,
      "total": 19,
      "prev_rank": 42,
      "prev_doubles": 1,
      "prev_homers": 4,
      "prev_total": 14,
      "rank_change": 17,
      "total_change": 5
    },
    {
      "rank": 25,
      "owner": "Bill Sarafolean",
      "team_name": "Bill Sarafolean",
      "doubles": 7,
      "homers": 12,
      "total": 19,
      "prev_rank": 23,
      "prev_doubles": 2,
      "prev_homers": 1,
      "prev_total": 16,
      "rank_change": -2,
      "total_change": 3
    },
    {
      "rank": 25,
      "owner": "Tim Brumm",
      "team_name": "Honey Badger #1",
      "doubles": 7,
      "homers": 12,
      "total": 19,
      "prev_rank": 46,
      "prev_doubles": 1,
      "prev_homers": 5,
      "prev_total": 13,
      "rank_change": 21,
      "total_change": 6
    },
    {
      "rank": 36,
      "owner": "Jon James",
      "team_name": "Jon James #1",
      "doubles": 10,
      "homers": 8,
      "total": 18,
      "prev_rank": 23,
      "prev_doubles": 1,
      "prev_homers": 1,
      "prev_total": 16,
      "rank_change": -13,
      "total_change": 2
    },
    {
      "rank": 36,
      "owner": "Shane Hoeft \ud83c\udfc6 ('20)",
      "team_name": "Hoffa3",
      "doubles": 10,
      "homers": 8,
      "total": 18,
      "prev_rank": 34,
      "prev_doubles": 2,
      "prev_homers": 1,
      "prev_total": 15,
      "rank_change": -2,
      "total_change": 3
    },
    {
      "rank": 36,
      "owner": "Joe Priestley",
      "team_name": "Joe Priestley #2",
      "doubles": 9,
      "homers": 9,
      "total": 18,
      "prev_rank": 23,
      "prev_doubles": 1,
      "prev_homers": 1,
      "prev_total": 16,
      "rank_change": -13,
      "total_change": 2
    },
    {
      "rank": 36,
      "owner": "Justin Bridge",
      "team_name": "Bridge 1",
      "doubles": 9,
      "homers": 9,
      "total": 18,
      "prev_rank": 46,
      "prev_doubles": 1,
      "prev_homers": 4,
      "prev_total": 13,
      "rank_change": 10,
      "total_change": 5
    },
    {
      "rank": 36,
      "owner": "Jim Macdonald",
      "team_name": "Juuuust A Bit Outside",
      "doubles": 8,
      "homers": 10,
      "total": 18,
      "prev_rank": 19,
      "prev_doubles": 1,
      "prev_homers": 0,
      "prev_total": 17,
      "rank_change": -17,
      "total_change": 1
    },
    {
      "rank": 36,
      "owner": "Clinton Shepherd",
      "team_name": "SHEP",
      "doubles": 8,
      "homers": 10,
      "total": 18,
      "prev_rank": 34,
      "prev_doubles": 1,
      "prev_homers": 2,
      "prev_total": 15,
      "rank_change": -2,
      "total_change": 3
    },
    {
      "rank": 36,
      "owner": "Mona Mitchell",
      "team_name": "Monami",
      "doubles": 7,
      "homers": 11,
      "total": 18,
      "prev_rank": 34,
      "prev_doubles": 1,
      "prev_homers": 2,
      "prev_total": 15,
      "rank_change": -2,
      "total_change": 3
    },
    {
      "rank": 36,
      "owner": "Becky Friedrich",
      "team_name": "Gold Dingers",
      "doubles": 6,
      "homers": 12,
      "total": 18,
      "prev_rank": 34,
      "prev_doubles": 1,
      "prev_homers": 2,
      "prev_total": 15,
      "rank_change": -2,
      "total_change": 3
    },
    {
      "rank": 36,
      "owner": "Debbie Hins",
      "team_name": "Debbie #1",
      "doubles": 6,
      "homers": 12,
      "total": 18,
      "prev_rank": 46,
      "prev_doubles": 2,
      "prev_homers": 3,
      "prev_total": 13,
      "rank_change": 10,
      "total_change": 5
    },
    {
      "rank": 45,
      "owner": "Ian Sullivan",
      "team_name": "Ian Sullivan 2",
      "doubles": 11,
      "homers": 6,
      "total": 17,
      "prev_rank": 46,
      "prev_doubles": 2,
      "prev_homers": 2,
      "prev_total": 13,
      "rank_change": 1,
      "total_change": 4
    },
    {
      "rank": 45,
      "owner": "Mike Erickson",
      "team_name": "Hallucinated Homers",
      "doubles": 10,
      "homers": 7,
      "total": 17,
      "prev_rank": 46,
      "prev_doubles": 2,
      "prev_homers": 2,
      "prev_total": 13,
      "rank_change": 1,
      "total_change": 4
    },
    {
      "rank": 45,
      "owner": "Kyle Vickerman",
      "team_name": "Vicks0",
      "doubles": 10,
      "homers": 7,
      "total": 17,
      "prev_rank": 46,
      "prev_doubles": 2,
      "prev_homers": 2,
      "prev_total": 13,
      "rank_change": 1,
      "total_change": 4
    },
    {
      "rank": 45,
      "owner": "Joe Priestley",
      "team_name": "Joe Priestley #3",
      "doubles": 9,
      "homers": 8,
      "total": 17,
      "prev_rank": 46,
      "prev_doubles": 2,
      "prev_homers": 2,
      "prev_total": 13,
      "rank_change": 1,
      "total_change": 4
    },
    {
      "rank": 45,
      "owner": "Bill Parent",
      "team_name": "Billy P",
      "doubles": 8,
      "homers": 9,
      "total": 17,
      "prev_rank": 34,
      "prev_doubles": 1,
      "prev_homers": 1,
      "prev_total": 15,
      "rank_change": -11,
      "total_change": 2
    },
    {
      "rank": 45,
      "owner": "Vickie Blomgren",
      "team_name": "Krack#22",
      "doubles": 8,
      "homers": 9,
      "total": 17,
      "prev_rank": 46,
      "prev_doubles": 1,
      "prev_homers": 3,
      "prev_total": 13,
      "rank_change": 1,
      "total_change": 4
    },
    {
      "rank": 45,
      "owner": "Dan Barfknecht",
      "team_name": "Dan Barfknecht #1",
      "doubles": 8,
      "homers": 9,
      "total": 17,
      "prev_rank": 61,
      "prev_doubles": 1,
      "prev_homers": 4,
      "prev_total": 12,
      "rank_change": 16,
      "total_change": 5
    },
    {
      "rank": 45,
      "owner": "Brett Morrison \ud83c\udfc6 ('25)",
      "team_name": "Brett Morrison #1",
      "doubles": 7,
      "homers": 10,
      "total": 17,
      "prev_rank": 73,
      "prev_doubles": 3,
      "prev_homers": 3,
      "prev_total": 11,
      "rank_change": 28,
      "total_change": 6
    },
    {
      "rank": 45,
      "owner": "Karl Pohl",
      "team_name": "Pohlcat",
      "doubles": 7,
      "homers": 10,
      "total": 17,
      "prev_rank": 73,
      "prev_doubles": 2,
      "prev_homers": 4,
      "prev_total": 11,
      "rank_change": 28,
      "total_change": 6
    },
    {
      "rank": 45,
      "owner": "Dennis L. Graves",
      "team_name": "Florida 2",
      "doubles": 7,
      "homers": 10,
      "total": 17,
      "prev_rank": 34,
      "prev_doubles": 0,
      "prev_homers": 2,
      "prev_total": 15,
      "rank_change": -11,
      "total_change": 2
    },
    {
      "rank": 45,
      "owner": "Danielle Macdonald \ud83c\udfc6 ('21)",
      "team_name": "The Queen of Diamonds",
      "doubles": 6,
      "homers": 11,
      "total": 17,
      "prev_rank": 34,
      "prev_doubles": 1,
      "prev_homers": 1,
      "prev_total": 15,
      "rank_change": -11,
      "total_change": 2
    },
    {
      "rank": 56,
      "owner": "Steve Swafford",
      "team_name": "Pain Relievers",
      "doubles": 15,
      "homers": 1,
      "total": 16,
      "prev_rank": 61,
      "prev_doubles": 4,
      "prev_homers": 0,
      "prev_total": 12,
      "rank_change": 5,
      "total_change": 4
    },
    {
      "rank": 56,
      "owner": "Mike Ammann",
      "team_name": "Ammann",
      "doubles": 12,
      "homers": 4,
      "total": 16,
      "prev_rank": 46,
      "prev_doubles": 2,
      "prev_homers": 1,
      "prev_total": 13,
      "rank_change": -10,
      "total_change": 3
    },
    {
      "rank": 56,
      "owner": "Jim Murray",
      "team_name": "Jim and Mark 2",
      "doubles": 10,
      "homers": 6,
      "total": 16,
      "prev_rank": 46,
      "prev_doubles": 1,
      "prev_homers": 2,
      "prev_total": 13,
      "rank_change": -10,
      "total_change": 3
    },
    {
      "rank": 56,
      "owner": "Thomas Murray",
      "team_name": "Eric Walters & Tom Murray #1",
      "doubles": 9,
      "homers": 7,
      "total": 16,
      "prev_rank": 90,
      "prev_doubles": 3,
      "prev_homers": 5,
      "prev_total": 8,
      "rank_change": 34,
      "total_change": 8
    },
    {
      "rank": 56,
      "owner": "Brian Larson",
      "team_name": "Brian Larson #1",
      "doubles": 8,
      "homers": 8,
      "total": 16,
      "prev_rank": 61,
      "prev_doubles": 2,
      "prev_homers": 2,
      "prev_total": 12,
      "rank_change": 5,
      "total_change": 4
    },
    {
      "rank": 56,
      "owner": "Cory Abrahamson",
      "team_name": "NoDak",
      "doubles": 8,
      "homers": 8,
      "total": 16,
      "prev_rank": 78,
      "prev_doubles": 2,
      "prev_homers": 4,
      "prev_total": 10,
      "rank_change": 22,
      "total_change": 6
    },
    {
      "rank": 56,
      "owner": "Josh Kallstrom",
      "team_name": "Josh K's Team",
      "doubles": 7,
      "homers": 9,
      "total": 16,
      "prev_rank": 61,
      "prev_doubles": 3,
      "prev_homers": 1,
      "prev_total": 12,
      "rank_change": 5,
      "total_change": 4
    },
    {
      "rank": 56,
      "owner": "Brett Morrison \ud83c\udfc6 ('25)",
      "team_name": "Brett Morrison #2",
      "doubles": 7,
      "homers": 9,
      "total": 16,
      "prev_rank": 73,
      "prev_doubles": 2,
      "prev_homers": 3,
      "prev_total": 11,
      "rank_change": 17,
      "total_change": 5
    },
    {
      "rank": 56,
      "owner": "Ryan Walters",
      "team_name": "Wally (Ryan Walters)",
      "doubles": 7,
      "homers": 9,
      "total": 16,
      "prev_rank": 42,
      "prev_doubles": 2,
      "prev_homers": 0,
      "prev_total": 14,
      "rank_change": -14,
      "total_change": 2
    },
    {
      "rank": 56,
      "owner": "Nick Hutchens",
      "team_name": "NickHutchens2",
      "doubles": 7,
      "homers": 9,
      "total": 16,
      "prev_rank": 46,
      "prev_doubles": 2,
      "prev_homers": 1,
      "prev_total": 13,
      "rank_change": -10,
      "total_change": 3
    },
    {
      "rank": 56,
      "owner": "Bill Schuldt",
      "team_name": "Dolla Billz",
      "doubles": 6,
      "homers": 10,
      "total": 16,
      "prev_rank": 78,
      "prev_doubles": 2,
      "prev_homers": 4,
      "prev_total": 10,
      "rank_change": 22,
      "total_change": 6
    },
    {
      "rank": 56,
      "owner": "Tyler Gorman",
      "team_name": "The Sadness Factory",
      "doubles": 3,
      "homers": 13,
      "total": 16,
      "prev_rank": 61,
      "prev_doubles": 1,
      "prev_homers": 3,
      "prev_total": 12,
      "rank_change": 5,
      "total_change": 4
    },
    {
      "rank": 68,
      "owner": "Nick Hutchens",
      "team_name": "NickHutchens1",
      "doubles": 9,
      "homers": 6,
      "total": 15,
      "prev_rank": 61,
      "prev_doubles": 2,
      "prev_homers": 1,
      "prev_total": 12,
      "rank_change": -7,
      "total_change": 3
    },
    {
      "rank": 68,
      "owner": "Tyler Harbin",
      "team_name": "Save Me Mr. Anthony",
      "doubles": 9,
      "homers": 6,
      "total": 15,
      "prev_rank": 61,
      "prev_doubles": 1,
      "prev_homers": 2,
      "prev_total": 12,
      "rank_change": -7,
      "total_change": 3
    },
    {
      "rank": 68,
      "owner": "Bill Schuldt",
      "team_name": "2$Billz",
      "doubles": 8,
      "homers": 7,
      "total": 15,
      "prev_rank": 46,
      "prev_doubles": 2,
      "prev_homers": 0,
      "prev_total": 13,
      "rank_change": -22,
      "total_change": 2
    },
    {
      "rank": 68,
      "owner": "Chris Tollefson",
      "team_name": "Tolly Llamas",
      "doubles": 7,
      "homers": 8,
      "total": 15,
      "prev_rank": 61,
      "prev_doubles": 2,
      "prev_homers": 1,
      "prev_total": 12,
      "rank_change": -7,
      "total_change": 3
    },
    {
      "rank": 68,
      "owner": "Mike Erickson",
      "team_name": "Deez Dongers",
      "doubles": 7,
      "homers": 8,
      "total": 15,
      "prev_rank": 46,
      "prev_doubles": 2,
      "prev_homers": 0,
      "prev_total": 13,
      "rank_change": -22,
      "total_change": 2
    },
    {
      "rank": 68,
      "owner": "Eric Dobervich",
      "team_name": "Doby Two",
      "doubles": 6,
      "homers": 9,
      "total": 15,
      "prev_rank": 61,
      "prev_doubles": 2,
      "prev_homers": 1,
      "prev_total": 12,
      "rank_change": -7,
      "total_change": 3
    },
    {
      "rank": 68,
      "owner": "Mark Walters",
      "team_name": "Mark and Jim 1",
      "doubles": 6,
      "homers": 9,
      "total": 15,
      "prev_rank": 78,
      "prev_doubles": 2,
      "prev_homers": 3,
      "prev_total": 10,
      "rank_change": 10,
      "total_change": 5
    },
    {
      "rank": 68,
      "owner": "Tom Ramy",
      "team_name": "C'mon Rick!",
      "doubles": 6,
      "homers": 9,
      "total": 15,
      "prev_rank": 78,
      "prev_doubles": 1,
      "prev_homers": 4,
      "prev_total": 10,
      "rank_change": 10,
      "total_change": 5
    },
    {
      "rank": 76,
      "owner": "Tim Brumm",
      "team_name": "Honey Badger #3",
      "doubles": 10,
      "homers": 4,
      "total": 14,
      "prev_rank": 73,
      "prev_doubles": 2,
      "prev_homers": 1,
      "prev_total": 11,
      "rank_change": -3,
      "total_change": 3
    },
    {
      "rank": 76,
      "owner": "Brian Larson",
      "team_name": "Brian Larson #2",
      "doubles": 8,
      "homers": 6,
      "total": 14,
      "prev_rank": 46,
      "prev_doubles": 1,
      "prev_homers": 0,
      "prev_total": 13,
      "rank_change": -30,
      "total_change": 1
    },
    {
      "rank": 76,
      "owner": "Ryan Dahl \ud83c\udfc6\ud83c\udfc6\ud83c\udfc6 ('19,'23,'24)",
      "team_name": "Ryan \u201cOpie\u201d Dahl #3",
      "doubles": 8,
      "homers": 6,
      "total": 14,
      "prev_rank": 61,
      "prev_doubles": 2,
      "prev_homers": 0,
      "prev_total": 12,
      "rank_change": -15,
      "total_change": 2
    },
    {
      "rank": 76,
      "owner": "Nicholas Waletich",
      "team_name": "Nashville Twins",
      "doubles": 7,
      "homers": 7,
      "total": 14,
      "prev_rank": 73,
      "prev_doubles": 2,
      "prev_homers": 1,
      "prev_total": 11,
      "rank_change": -3,
      "total_change": 3
    },
    {
      "rank": 76,
      "owner": "Shane Hoeft \ud83c\udfc6 ('20)",
      "team_name": "Hoffa1",
      "doubles": 7,
      "homers": 7,
      "total": 14,
      "prev_rank": 78,
      "prev_doubles": 2,
      "prev_homers": 2,
      "prev_total": 10,
      "rank_change": 2,
      "total_change": 4
    },
    {
      "rank": 76,
      "owner": "Justin Fryklund",
      "team_name": "Fryklund",
      "doubles": 5,
      "homers": 9,
      "total": 14,
      "prev_rank": 78,
      "prev_doubles": 1,
      "prev_homers": 3,
      "prev_total": 10,
      "rank_change": 2,
      "total_change": 4
    },
    {
      "rank": 76,
      "owner": "Dustin Dupont",
      "team_name": "BangBang",
      "doubles": 5,
      "homers": 9,
      "total": 14,
      "prev_rank": 46,
      "prev_doubles": 1,
      "prev_homers": 0,
      "prev_total": 13,
      "rank_change": -30,
      "total_change": 1
    },
    {
      "rank": 76,
      "owner": "Carolyn Himes",
      "team_name": "Team 1 (CH)",
      "doubles": 4,
      "homers": 10,
      "total": 14,
      "prev_rank": 86,
      "prev_doubles": 1,
      "prev_homers": 4,
      "prev_total": 9,
      "rank_change": 10,
      "total_change": 5
    },
    {
      "rank": 84,
      "owner": "Brett Walters & Eric Miras",
      "team_name": "Brett Walters & Eric Miras",
      "doubles": 6,
      "homers": 7,
      "total": 13,
      "prev_rank": 78,
      "prev_doubles": 1,
      "prev_homers": 2,
      "prev_total": 10,
      "rank_change": -6,
      "total_change": 3
    },
    {
      "rank": 84,
      "owner": "Jon James",
      "team_name": "Jon James #3",
      "doubles": 5,
      "homers": 8,
      "total": 13,
      "prev_rank": 61,
      "prev_doubles": 1,
      "prev_homers": 0,
      "prev_total": 12,
      "rank_change": -23,
      "total_change": 1
    },
    {
      "rank": 86,
      "owner": "Jake Luedtke",
      "team_name": "JD's NL Burners",
      "doubles": 9,
      "homers": 3,
      "total": 12,
      "prev_rank": 86,
      "prev_doubles": 2,
      "prev_homers": 1,
      "prev_total": 9,
      "rank_change": 0,
      "total_change": 3
    },
    {
      "rank": 86,
      "owner": "Shane Hoeft \ud83c\udfc6 ('20)",
      "team_name": "Hoffa2",
      "doubles": 8,
      "homers": 4,
      "total": 12,
      "prev_rank": 90,
      "prev_doubles": 3,
      "prev_homers": 1,
      "prev_total": 8,
      "rank_change": 4,
      "total_change": 4
    },
    {
      "rank": 86,
      "owner": "Conner Tokheim",
      "team_name": "Conner Tokheim #2",
      "doubles": 7,
      "homers": 5,
      "total": 12,
      "prev_rank": 61,
      "prev_doubles": 0,
      "prev_homers": 0,
      "prev_total": 12,
      "rank_change": -25,
      "total_change": 0
    },
    {
      "rank": 86,
      "owner": "Nick Todora",
      "team_name": "Gamers",
      "doubles": 7,
      "homers": 5,
      "total": 12,
      "prev_rank": 78,
      "prev_doubles": 2,
      "prev_homers": 0,
      "prev_total": 10,
      "rank_change": -8,
      "total_change": 2
    },
    {
      "rank": 90,
      "owner": "Jason Elasky",
      "team_name": "Kandiyohi Pheasant Chasers",
      "doubles": 8,
      "homers": 3,
      "total": 11,
      "prev_rank": 93,
      "prev_doubles": 3,
      "prev_homers": 1,
      "prev_total": 7,
      "rank_change": 3,
      "total_change": 4
    },
    {
      "rank": 90,
      "owner": "Troy Wasiloski",
      "team_name": "Waz's Bomb Squad",
      "doubles": 6,
      "homers": 5,
      "total": 11,
      "prev_rank": 90,
      "prev_doubles": 2,
      "prev_homers": 1,
      "prev_total": 8,
      "rank_change": 0,
      "total_change": 3
    },
    {
      "rank": 90,
      "owner": "Justin Bridge",
      "team_name": "Bridge 2",
      "doubles": 4,
      "homers": 7,
      "total": 11,
      "prev_rank": 86,
      "prev_doubles": 1,
      "prev_homers": 1,
      "prev_total": 9,
      "rank_change": -4,
      "total_change": 2
    },
    {
      "rank": 90,
      "owner": "John Hackett",
      "team_name": "Hackdawg",
      "doubles": 3,
      "homers": 8,
      "total": 11,
      "prev_rank": 93,
      "prev_doubles": 1,
      "prev_homers": 3,
      "prev_total": 7,
      "rank_change": 3,
      "total_change": 4
    },
    {
      "rank": 94,
      "owner": "Eric Dobervich",
      "team_name": "Doby One",
      "doubles": 5,
      "homers": 5,
      "total": 10,
      "prev_rank": 96,
      "prev_doubles": 2,
      "prev_homers": 2,
      "prev_total": 6,
      "rank_change": 2,
      "total_change": 4
    },
    {
      "rank": 94,
      "owner": "Cory Abrahamson",
      "team_name": "Nodak 3",
      "doubles": 5,
      "homers": 5,
      "total": 10,
      "prev_rank": 86,
      "prev_doubles": 1,
      "prev_homers": 0,
      "prev_total": 9,
      "rank_change": -8,
      "total_change": 1
    },
    {
      "rank": 94,
      "owner": "Brian McBride",
      "team_name": "Brian McBride #1",
      "doubles": 3,
      "homers": 7,
      "total": 10,
      "prev_rank": 93,
      "prev_doubles": 2,
      "prev_homers": 1,
      "prev_total": 7,
      "rank_change": -1,
      "total_change": 3
    },
    {
      "rank": 97,
      "owner": "Joel Obermeyer",
      "team_name": "Pipe City",
      "doubles": 4,
      "homers": 5,
      "total": 9,
      "prev_rank": 96,
      "prev_doubles": 2,
      "prev_homers": 1,
      "prev_total": 6,
      "rank_change": -1,
      "total_change": 3
    }
  ]
}